PyResilient/__init__.py
PyResilient/fallback.py
PyResilient/retry.py
PyResilient/timeout.py
PyResilient/handlers/__init__.py
PyResilient/handlers/base_handler.py
PyResilient/handlers/fallback_handler.py
PyResilient/handlers/timeout_handler.py
PyResilient/strategies/__init__.py
PyResilient/strategies/fallback_strategies.py
PyResilient/strategies/timeout_strategies.py
PyResilient-0.0.5.dist-info/LICENSE
PyResilient-0.0.5.dist-info/METADATA
PyResilient-0.0.5.dist-info/WHEEL
PyResilient-0.0.5.dist-info/top_level.txt
PyResilient-0.0.5.dist-info/RECORD
