Metadata-Version: 2.1
Name: PyResilient
Version: 0.0.5
Summary: A Python library for handling retries, timeouts and fallbacks in a resilient way.
Author-email: Bastián García <bastiang@uc.cl>
Maintainer-email: Bastián García <bastiang@uc.cl>
License: MIT
Classifier: Programming Language :: Python :: 3
Classifier: License :: OSI Approved :: MIT License
Classifier: Operating System :: OS Independent
Requires-Python: >=3.8
License-File: LICENSE
